xkcdrandom/__about__.py
xkcdrandom/__init__.py
xkcdrandom/__main__.py
xkcdrandom/grn.py
xkcdrandom-0.0.2.dist-info/METADATA
xkcdrandom-0.0.2.dist-info/WHEEL
xkcdrandom-0.0.2.dist-info/licenses/LICENSE.txt
xkcdrandom-0.0.2.dist-info/RECORD
